Compiled from "ProfiledSystemB.java"
public class com.artemis.system.ProfiledSystemB extends com.artemis.systems.VoidEntitySystem {
  private final com.artemis.util.SimpleProfiler $profiler;

  public int execution;

  protected void initialize();
    Code:
       0: aload_0       
       1: new           #13                 // class com/artemis/util/SimpleProfiler
       4: dup           
       5: invokespecial #16                 // Method com/artemis/util/SimpleProfiler."<init>":()V
       8: putfield      #18                 // Field $profiler:Lcom/artemis/util/SimpleProfiler;
      11: aload_0       
      12: getfield      #18                 // Field $profiler:Lcom/artemis/util/SimpleProfiler;
      15: aload_0       
      16: aload_0       
      17: getfield      #22                 // Field world:Lcom/artemis/World;
      20: invokevirtual #25                 // Method com/artemis/util/SimpleProfiler.initialize:(Lcom/artemis/BaseSystem;Lcom/artemis/World;)V
      23: return        

  public com.artemis.system.ProfiledSystemB();
    Code:
       0: aload_0       
       1: invokespecial #26                 // Method com/artemis/systems/VoidEntitySystem."<init>":()V
       4: return        

  protected void processSystem();
    Code:
       0: return        

  protected void begin();
    Code:
       0: aload_0       
       1: getfield      #18                 // Field $profiler:Lcom/artemis/util/SimpleProfiler;
       4: invokevirtual #33                 // Method com/artemis/util/SimpleProfiler.start:()V
       7: aload_0       
       8: dup           
       9: getfield      #35                 // Field execution:I
      12: iconst_1      
      13: iadd          
      14: putfield      #35                 // Field execution:I
      17: return        

  protected void end();
    Code:
       0: aload_0       
       1: getfield      #35                 // Field execution:I
       4: iconst_1      
       5: if_icmpne     16
       8: aload_0       
       9: getfield      #18                 // Field $profiler:Lcom/artemis/util/SimpleProfiler;
      12: invokevirtual #39                 // Method com/artemis/util/SimpleProfiler.stop:()V
      15: return        
      16: aload_0       
      17: getfield      #35                 // Field execution:I
      20: iconst_1      
      21: if_icmpne     27
      24: invokestatic  #44                 // Method org/junit/Assert.fail:()V
      27: aload_0       
      28: getfield      #18                 // Field $profiler:Lcom/artemis/util/SimpleProfiler;
      31: invokevirtual #39                 // Method com/artemis/util/SimpleProfiler.stop:()V
      34: return        
}
